colab_frp/__init__.py
colab_frp/frp.py
colab_frp-0.0.6.dist-info/LICENSE
colab_frp-0.0.6.dist-info/METADATA
colab_frp-0.0.6.dist-info/WHEEL
colab_frp-0.0.6.dist-info/top_level.txt
colab_frp-0.0.6.dist-info/RECORD
