Metadata-Version: 2.1
Name: colab-frp
Version: 0.0.6
Summary: Google colab frp connector
Home-page: https://github.com/WassimBenzarti/colab-ssh-connector.git
Author: argszero
Author-email: argszero@gmail.com
License: UNKNOWN
Platform: UNKNOWN
Classifier: Programming Language :: Python :: 3
Classifier: License :: OSI Approved :: Apache Software License
Classifier: Operating System :: OS Independent
Requires-Python: >=3.6
